HISTORY.md
LICENSE
MANIFEST.in
README.md
setup.py
wsgi_request_id.py
wsgi_request_id.egg-info/PKG-INFO
wsgi_request_id.egg-info/SOURCES.txt
wsgi_request_id.egg-info/dependency_links.txt
wsgi_request_id.egg-info/not-zip-safe
wsgi_request_id.egg-info/top_level.txt