Metadata-Version: 1.1
Name: wsgi-request-id
Version: 0.2
Summary: Extract yourself some Request IDs.
Home-page: http://github.com/rhyselsmore/wsgi-request-id
Author: Rhys Elsmore
Author-email: me@rhys.io
License: The ISC License (ISC)
